{
  "descriptors": [
    {
      "id": 1,
      "word": "macabre",
      "synonyms": [
        "mummified",
        "desiccated",
        "preserved",
        "nightmarish",
        "macabre",
        "dead",
        "decaying",
        "withering"
      ]
    },
    {
      "id": 2,
      "word": "foreign",
      "synonyms": [
        "foreign",
        "unknown",
        "far-off",
        "planar",
        "celestial",
        "abyssal",
        "faraway",
        "remote",
        "outlying"
      ]
    },
    {
      "id": 3,
      "word": "scary",
      "synonyms": [
        "unsettling",
        "scary",
        "alarming",
        "creepy",
        "shocking",
        "horrendous",
        "disquieting",
        "perplexing",
        "troubling",
        "worrisome",
        "startling",
        "ominous",
        "foreboding",
        "sinister",
        "shocking",
        "unnerving",
        "disquieting",
        "perplexing",
        "troubling",
        "worrisome",
        "startling",
        "ominous",
        "foreboding"
      ]
    },
    {
      "id": 4,
      "word": "ancient",
      "synonyms": [
        "old",
        "ancient",
        "age-old",
        "old-fashioned",
        "timeworn",
        "aged",
        "relic",
        "antediluvian",
        "antique"
      ]
    },
    {
      "id": 5,
      "word": "childlike",
      "synonyms": [
        "childlike",
        "small",
        "cute",
        "innocent",
        "cudly",
        "simple",
        "delightful",
        "dainty",
        "adorable",
        "charming"
      ]
    },
    {
      "id": 6,
      "word": "lostInBattle",
      "synonyms": [
        "dead",
        "lost",
        "missing",
        "deceased",
        "late"
      ]
    },
    {
      "id": 7,
      "word": "ornate",
      "synonyms": [
        "jeweled",
        "gilded",
        "ornate",
        "decorated",
        "elegant",
        "gaudy",
        "fancy",
        "opulent",
        "magnificent",
        "dazzling",
        "ornamented",
        "resplendent"
      ]
    },
    {
      "id": 8,
      "word": "colorsBase",
      "synonyms": [
        "white",
        "gray",
        "black",
        "brown",
        "beige",
        "blue",
        "red",
        "pink",
        "green",
        "yellow",
        "orange",
        "violet",
        "indigo"
      ]
    },
    {
      "id": 9,
      "word": "material",
      "synonyms": [
        "metal",
        "wooden",
        "clay",
        "stone",
        "bone",
        "ivory"
      ]
    },
    {
      "id": 10,
      "word": "gravelyIll",
      "synonyms": [
        "sick",
        "ill",
        "frail",
        "dying",
        "bone",
        "ivory",
        "ailing",
        "feeble",
        "infirm",
        "diseased"
      ]
    },
    {
      "id": 11,
      "word": "kindly",
      "synonyms": [
        "kindly",
        "thoughtful",
        "good-hearted",
        "gentle",
        "kind",
        "good-natured",
        "kindhearted"
      ]
    },
    {
      "id": 12,
      "word": "weird",
      "synonyms": [
        "strange",
        "weird",
        "creepy",
        "curious",
        "freaky",
        "mysterious",
        "spooky",
        "unnatural"
      ]
    },
    {
      "id": 13,
      "word": "feelsLike",
      "synonyms": [
        "warm",
        "wet",
        "slimy",
        "prickly",
        "cold",
        "icy",
        "burning"
      ]
    },
    {
      "id": 14,
      "word": "glistening",
      "synonyms": [
        "glistening",
        "blazing",
        "flaming",
        "glittering",
        "luminous",
        "shimmering",
        "lustrous",
        "glowing",
        "shiny",
        "lustrous",
        "scintillating"
      ]
    },
    {
      "id": 15,
      "word": "geometric",
      "synonyms": [
        "cylindrical",
        "cubic",
        "square",
        "ring-shaped",
        "spherical",
        "conical",
        "linear",
        "pentagonal",
        "hexagonal",
        "icosahedronal",
        "octagonal",
        "rectangular",
        "triangular",
        "pyramid-shaped",
        "circular",
        "geometric"
      ]
    },
    {
      "id": 16,
      "word": "itemType",
      "synonyms": [
        "mystical",
        "magical",
        "mechanical",
        "simple",
        "celestial",
        "mundane",
        "complex",
        "automated",
        "pragmatic"
      ]
    },
    {
      "id": 17,
      "word": "hornShapes",
      "synonyms": [
        "curving downward",
        "tips flaring up",
        "curving upwards",
        "curving slightly backwards in an arc",
        "curving backwards",
        "straight upward",
        "straight forward",
        "curving upwards in a smooth arc",
        "curving outwards in a smooth arc",
        "curving downwards in a smooth arc",
        "curving outward",
        "curving upward in a sweeping arc",
        "cork-screw twists",
        "curved",
        "conical",
        "sharply curved",
        "heavily ridged",
        "spiral",
        "hook-shaped",
        "curved upwards then inwards",
        "gently curved"
      ]
    },
    {
      "id": 17,
      "word": "hornDescriptors",
      "synonyms": [
        "sturdy",
        "smooth",
        "long",
        "short",
        "tiny",
        "shiny",
        "tapered",
        "small",
        "compact",
        "big",
        "heavy",
        "slender",
        "sturdy",
        "thick",
        "immense"
      ]
    },
    {
      "id": 18,
      "word": "colorHueWhite",
      "synonyms": [
        "white",
        "alabaster",
        "snow",
        "ivory",
        "cream",
        "chalk",
        "pearl",
        "linen",
        "eggshell",
        "cotton",
        "marshmallow",
        "vanilla",
        "magnolia",
        "porcelain",
        "antique",
        "seashell",
        "daisy",
        "coconut",
        "ghost",
        "frost"
      ]
    },
    {
      "id": 19,
      "word": "colorHueGray",
      "synonyms": [
        "charcoal",
        "slate",
        "gunmetal",
        "ash",
        "gray",
        "steel",
        "iron",
        "pewter",
        "silver",
        "smoke",
        "dove",
        "stone",
        "fog",
        "graphite",
        "anchor",
        "shadow",
        "flint",
        "oyster",
        "cool",
        "warm",
        "platinum"
      ]
    },
    {
      "id": 20,
      "word": "colorHueBlack",
      "synonyms": [
        "jet",
        "charcoal",
        "midnight",
        "ink",
        "onyx",
        "black",
        "obsidian",
        "smoke",
        "shadow",
        "raven",
        "sable",
        "pitch",
        "ebony"
      ]
    },
    {
      "id": 21,
      "word": "colorHueBrown",
      "synonyms": [
        "sienna",
        "taupe",
        "sepia",
        "burnt sienna",
        "umber",
        "brown",
        "beige",
        "mahogany",
        "caramel",
        "tawny",
        "bronze",
        "walnut",
        "cinnamon",
        "mocha",
        "mocha",
        "khaki"
      ]
    },
    {
      "id": 22,
      "word": "colorHueBlue",
      "synonyms": [
        "sky",
        "teal",
        "cornflower",
        "cerulean",
        "sapphire",
        "navy",
        "azure",
        "blue",
        "teal",
        "indigo",
        "baby",
        "midnight",
        "royal",
        "prussian",
        "periwinkle",
        "cobalt",
        "turquoise"
      ]
    },
    {
      "id": 23,
      "word": "colorHueRed",
      "synonyms": [
        "crimson",
        "scarlet",
        "burgundy",
        "maroon",
        "red",
        "vermilion",
        "carmine",
        "fire brick",
        "cherry",
        "coral",
        "tomato",
        "cardinal",
        "rose",
        "sangria",
        "raspberry"
      ]
    },
    {
      "id": 24,
      "word": "colorHuePink",
      "synonyms": [
        "pink",
        "blush",
        "rose",
        "magenta",
        "flamingo",
        "fuchsia",
        "ballet",
        "cherry blossom",
        "hot",
        "raspberry",
        "baby",
        "petal",
        "coral",
        "bubble gum"
      ]
    },
    {
      "id": 25,
      "word": "colorHueGreen",
      "synonyms": [
        "emerald",
        "forest",
        "hunter",
        "kelly",
        "seafoam",
        "lime",
        "pistachio",
        "chartreuse",
        "jade",
        "fern",
        "moss",
        "sage",
        "green",
        "olive",
        "mint"
      ]
    },
    {
      "id": 26,
      "word": "colorHueOrange",
      "synonyms": [
        "mango",
        "orange",
        "carrot",
        "amber",
        "sunset",
        "tangerine",
        "marigold",
        "persimmon",
        "apricot",
        "rust",
        "peach",
        "pumpkin"
      ]
    },
    {
      "id": 27,
      "word": "colorHueYellow",
      "synonyms": [
        "lemon",
        "canary",
        "daffodil",
        "maize",
        "flaxen",
        "honey",
        "mustard",
        "citrine",
        "gold",
        "banana",
        "butter",
        "saffron",
        "sunflower"
      ]
    },
    {
      "id": 28,
      "word": "colorHueViolet",
      "synonyms": [
        "lavender",
        "amethyst",
        "lilac",
        "mauve",
        "royal",
        "grape",
        "purple",
        "plum",
        "mulberry",
        "wisteria",
        "Byzantine",
        "fuchsia",
        "orchid",
        "eggplant",
        "periwinkle",
        "heliotrope",
        "violet"
      ]
    }
  ]
}

